fsleyes_props/__init__.py
fsleyes_props/bindable.py
fsleyes_props/build.py
fsleyes_props/build_parts.py
fsleyes_props/cache.py
fsleyes_props/callqueue.py
fsleyes_props/cli.py
fsleyes_props/properties.py
fsleyes_props/properties_types.py
fsleyes_props/properties_value.py
fsleyes_props/serialise.py
fsleyes_props/suppress.py
fsleyes_props/syncable.py
fsleyes_props/trace.py
fsleyes_props/widgets.py
fsleyes_props/widgets_boolean.py
fsleyes_props/widgets_bounds.py
fsleyes_props/widgets_choice.py
fsleyes_props/widgets_list.py
fsleyes_props/widgets_number.py
fsleyes_props/widgets_point.py
fsleyes_props/tests/__init__.py
fsleyes_props/tests/test_bindable.py
fsleyes_props/tests/test_cache.py
fsleyes_props/tests/test_callqueue.py
fsleyes_props/tests/test_hasprops.py
fsleyes_props/tests/test_importall.py
fsleyes_props/tests/test_properties_value.py
fsleyes_props/tests/test_property_colourmap.py
fsleyes_props/tests/test_property_number.py
fsleyes_props/tests/test_property_overwritten.py
fsleyes_props/tests/test_property_string.py
fsleyes_props/tests/test_property_types.py
fsleyes_props/tests/test_suppress.py
fsleyes_props/tests/test_syncable.py
fsleyes_props/tests/test_widget_boolean.py
fsleyes_props/tests/test_widget_bounds.py
fsleyes_props/tests/test_widget_number.py
fsleyes_props/tests/test_widget_point.py
fsleyes_props/tests/testdata/false.png
fsleyes_props/tests/testdata/true.png
fsleyes_props-1.12.2.dist-info/licenses/LICENSE
fsleyes_props-1.12.2.dist-info/METADATA
fsleyes_props-1.12.2.dist-info/WHEEL
fsleyes_props-1.12.2.dist-info/top_level.txt
fsleyes_props-1.12.2.dist-info/RECORD
