Metadata-Version: 2.4
Name: fsleyes-props
Version: 1.12.2
Summary: [wx]Python event programming framework
Author-email: Paul McCarthy <pauldmccarthy@gmail.com>
Project-URL: Repository, https://git.fmrib.ox.ac.uk/fsl/fsleyes/props
Project-URL: Documentation, https://open.win.ox.ac.uk/pages/fsl/fsleyes/props/
Requires-Python: >=3.8
License-File: LICENSE
Requires-Dist: numpy
Requires-Dist: matplotlib>=3.5
Requires-Dist: wxPython>=3.0.2.0
Requires-Dist: fsleyes-widgets>=0.6
Requires-Dist: fslpy>=1.4
Provides-Extra: doc
Requires-Dist: sphinx; extra == "doc"
Requires-Dist: sphinx_rtd_theme; extra == "doc"
Provides-Extra: test
Requires-Dist: pytest; extra == "test"
Requires-Dist: coverage; extra == "test"
Requires-Dist: pytest-cov; extra == "test"
Requires-Dist: tomli; python_version < "3.11" and extra == "test"
Provides-Extra: style
Requires-Dist: pylint; extra == "style"
Requires-Dist: flake8; extra == "style"
Dynamic: license-file
